aws_ssh_sync/__init__.py
aws_ssh_sync/main.py
tests/__init__.py
tests/conftest.py
tests/test_config.py
tests/test_docs.py
tests/test_file_output.py
aws_ssh_sync-0.3.0.dist-info/LICENSE
aws_ssh_sync-0.3.0.dist-info/METADATA
aws_ssh_sync-0.3.0.dist-info/WHEEL
aws_ssh_sync-0.3.0.dist-info/entry_points.txt
aws_ssh_sync-0.3.0.dist-info/top_level.txt
aws_ssh_sync-0.3.0.dist-info/RECORD
