Metadata-Version: 2.1
Name: aws-ssh-sync
Version: 0.3.0
Summary: Generate 'ssh_config' files, based on current Amazon EC2 state.
Home-page: https://github.com/sbilinski/aws-ssh-sync
Author: Szymon Biliński
Author-email: szymon.bilinski@gmail.com
License: UNKNOWN
Platform: UNKNOWN
Classifier: Topic :: System :: Networking
Classifier: License :: OSI Approved :: Apache Software License
Classifier: Operating System :: POSIX
Requires-Python: >=3.6
Requires-Dist: boto3 (>=1.9)
